{"is_source_file": true, "file_id": 27, "git_revision": "", "state": 1, "description": "", "external_files": [], "external_methods": [], "published": [], "classes": [], "methods": [], "calls": [], "search-terms": [], "ctags": [{"_type": "tag", "name": "express", "path": "/home/kavia/workspace/code-generation/recipe-explorer-38071-38143/frontend_app/scripts/static-server.js", "pattern": "/^const express = require('express');$/", "language": "JavaScript", "kind": "constant"}, {"_type": "tag", "name": "main", "path": "/home/kavia/workspace/code-generation/recipe-explorer-38071-38143/frontend_app/scripts/static-server.js", "pattern": "/^function main() {$/", "language": "JavaScript", "kind": "function", "signature": "()"}], "format": "JavaScript", "hash": "a53018186d28172b63ee4074235da51c", "format-version": 4, "code-base-name": "frontend_app", "filename": "frontend_app/scripts/static-server.js", "knowledge_revision": 153}