{"is_source_file": false, "format": "", "description": "", "external_files": [], "external_methods": [], "published": [], "classes": [], "methods": [], "calls": [], "search-terms": [], "state": 2, "file_id": 6, "knowledge_revision": 229, "git_revision": "93d0731bf22c72605c2079f3762dce6c1c2c2c7d", "hash": "d568ff9ad82a588a545f7206a9e02a78", "format-version": 4, "code-base-name": "frontend_app", "filename": "frontend_app/package.json", "revision_history": [{"229": "93d0731bf22c72605c2079f3762dce6c1c2c2c7d"}]}