{"is_source_file": false, "format": "", "description": "", "external_files": [], "external_methods": [], "published": [], "classes": [], "methods": [], "calls": [], "search-terms": [], "state": 2, "file_id": 6, "knowledge_revision": 237, "git_revision": "1ef0e022901b2d257d358f6037493345c4d8d5a8", "hash": "fa93e8815d66ea7403d5f084d0cd41a6", "format-version": 4, "code-base-name": "frontend_app", "filename": "frontend_app/package.json", "revision_history": [{"237": "1ef0e022901b2d257d358f6037493345c4d8d5a8"}]}